auto_graph_of_thoughts/__init__.py
auto_graph_of_thoughts/baseline/__init__.py
auto_graph_of_thoughts/baseline/baseline_config.py
auto_graph_of_thoughts/baseline/baseline_strategy.py
auto_graph_of_thoughts/baseline/baseline_strategy_exception.py
auto_graph_of_thoughts/baseline/graph_generator.py
auto_graph_of_thoughts/baseline/input_output_baseline_strategy.py
auto_graph_of_thoughts/baseline/random_baseline_strategy.py
auto_graph_of_thoughts/baseline/simulated_annealing_baseline_config.py
auto_graph_of_thoughts/baseline/simulated_annealing_baseline_strategy.py
auto_graph_of_thoughts/baseline/model/__init__.py
auto_graph_of_thoughts/baseline/model/baseline_iteration_result.py
auto_graph_of_thoughts/baseline/model/baseline_meta_info.py
auto_graph_of_thoughts/baseline/model/baseline_result_summary.py
auto_graph_of_thoughts/controller/__init__.py
auto_graph_of_thoughts/controller/continuous_graph_controller.py
auto_graph_of_thoughts/controller/layer_action_result.py
auto_graph_of_thoughts/env/__init__.py
auto_graph_of_thoughts/env/action_type.py
auto_graph_of_thoughts/env/graph_observation_component.py
auto_graph_of_thoughts/env/graph_of_thoughts_env.py
auto_graph_of_thoughts/env/graph_step_reward.py
auto_graph_of_thoughts/env/graph_step_reward_version.py
auto_graph_of_thoughts/env/layer_action.py
auto_graph_of_thoughts/env/wrapper/__init__.py
auto_graph_of_thoughts/env/wrapper/box_obs_filter_wrapper.py
auto_graph_of_thoughts/env/wrapper/dict_obs_filter_wrapper.py
auto_graph_of_thoughts/env/wrapper/env_wrapper_exception.py
auto_graph_of_thoughts/env/wrapper/ordinal_discrete_obs_filter_wrapper.py
auto_graph_of_thoughts/env/wrapper/ordinal_discrete_to_discrete_obs_mapping_wrapper.py
auto_graph_of_thoughts/experiment/__init__.py
auto_graph_of_thoughts/experiment/agent_evaluation.py
auto_graph_of_thoughts/experiment/agent_evaluation_summary.py
auto_graph_of_thoughts/experiment/episode.py
auto_graph_of_thoughts/experiment/evaluate_agent.py
auto_graph_of_thoughts-1.2.1.dist-info/METADATA
auto_graph_of_thoughts-1.2.1.dist-info/WHEEL
auto_graph_of_thoughts-1.2.1.dist-info/licenses/LICENSE
auto_graph_of_thoughts-1.2.1.dist-info/RECORD
