Metadata-Version: 2.4
Name: auto-graph-of-thoughts
Version: 1.2.1
Summary: Automated Graph of Thoughts
Project-URL: Repository, https://github.com/mriesen/auto-graph-of-thoughts.git
Author-email: Manuel Riesen <manuelnoah.riesen@students.bfh.ch>
Maintainer-email: Manuel Riesen <manuel.riesen0@gmail.com>
License-File: LICENSE
Classifier: Development Status :: 3 - Alpha
Classifier: Programming Language :: Python
Classifier: Programming Language :: Python :: 3.11
Classifier: Programming Language :: Python :: 3.12
Classifier: Topic :: Scientific/Engineering :: Artificial Intelligence
Requires-Python: >=3.11
Requires-Dist: gymnasium<1.0.0,>=0.29.1
Requires-Dist: numpy<2.0.0,>=1.26.4
Requires-Dist: pure-graph-of-thoughts<2.0.0,>=1.3.0
Provides-Extra: notebooks
Requires-Dist: jupyter<2.0.0,>=1.1.0; extra == 'notebooks'
Requires-Dist: pandas<3.0.0,>=2.2.1; extra == 'notebooks'
Requires-Dist: plotly<6.0.0,>=5.20.0; extra == 'notebooks'
Requires-Dist: pure-graph-of-thoughts[visualization,visualization-dot]<2.0.0,>=1.3.0; extra == 'notebooks'
Requires-Dist: stable-baselines3<3.0.0,>=2.2.1; extra == 'notebooks'
Requires-Dist: tensorboard<3.0.0,>=2.16.2; extra == 'notebooks'
